[
  {
    "d": {
"identity": 108,
"labels": [
        "Person"
      ],
"properties": {
"born": 1965,
"name": "Tom Tykwer"
      }
    }
  },
  {
    "d": {
"identity": 6,
"labels": [
        "Person"
      ],
"properties": {
"born": 1965,
"name": "Lana Wachowski"
      }
    }
  },
  {
    "d": {
"identity": 5,
"labels": [
        "Person"
      ],
"properties": {
"born": 1967,
"name": "Lilly Wachowski"
      }
    }
  },
  {
    "d": {
"identity": 25,
"labels": [
        "Person"
      ],
"properties": {
"born": 1967,
"name": "James Marshall"
      }
    }
  },
  {
    "d": {
"identity": 196,
"labels": [
        "Person"
      ],
"properties": {
"born": 1967,
"name": "James Marshall"
      }
    }
  },
  {
    "d": {
"identity": 176,
"labels": [
        "Person"
      ],
"properties": {
"born": 1967,
"name": "Lilly Wachowski"
      }
    }
  },
  {
    "d": {
"identity": 177,
"labels": [
        "Person"
      ],
"properties": {
"born": 1965,
"name": "Lana Wachowski"
      }
    }
  },
  {
    "d": {
"identity": 279,
"labels": [
        "Person"
      ],
"properties": {
"born": 1965,
"name": "Tom Tykwer"
      }
    }
  },
  {
    "d": {
"identity": 347,
"labels": [
        "Person"
      ],
"properties": {
"born": 1967,
"name": "Lilly Wachowski"
      }
    }
  },
  {
    "d": {
"identity": 348,
"labels": [
        "Person"
      ],
"properties": {
"born": 1965,
"name": "Lana Wachowski"
      }
    }
  },
  {
    "d": {
"identity": 450,
"labels": [
        "Person"
      ],
"properties": {
"born": 1965,
"name": "Tom Tykwer"
      }
    }
  },
  {
    "d": {
"identity": 367,
"labels": [
        "Person"
      ],
"properties": {
"born": 1967,
"name": "James Marshall"
      }
    }
  },
  {
    "d": {
"identity": 519,
"labels": [
        "Person"
      ],
"properties": {
"born": 1965,
"name": "Lana Wachowski"
      }
    }
  },
  {
    "d": {
"identity": 518,
"labels": [
        "Person"
      ],
"properties": {
"born": 1967,
"name": "Lilly Wachowski"
      }
    }
  },
  {
    "d": {
"identity": 621,
"labels": [
        "Person"
      ],
"properties": {
"born": 1965,
"name": "Tom Tykwer"
      }
    }
  },
  {
    "d": {
"identity": 538,
"labels": [
        "Person"
      ],
"properties": {
"born": 1967,
"name": "James Marshall"
      }
    }
  }
]